{
  "schema_version": 1,
  "updated_at": "2026-05-21T10:04:12+00:00",
  "revision": 29,
  "check_policy": "target_channel_must_have_active_join_bot_admin",
  "description": "转发前对目标频道 getChatAdministrators；若任一管理员 user.username（忽略大小写、无@）在本列表 bot_username 中，才允许 copyMessage。",
  "active_bot_ids": [
    4,
    5
  ],
  "active_bot_usernames": [
    "ainivipbot",
    "haijiaoVIP1001_bot"
  ],
  "tenants": [
    {
      "bot_id": 4,
      "bot_username": "ainivipbot",
      "bot_username_norm": "ainivipbot",
      "expire_at": 1810832814
    },
    {
      "bot_id": 5,
      "bot_username": "haijiaoVIP1001_bot",
      "bot_username_norm": "haijiaovip1001_bot",
      "expire_at": 1810882405
    }
  ]
}